{"namedChunkGroups":{"polyfill":{"name":"polyfill","assets":[{"name":"webpack-runtime-37ea483c46c3e5d7bb05.js","size":5204},{"name":"polyfill-2a1c0a52cb0b7a0205e1.js","size":82629}],"filteredAssets":0,"assetsSize":87833,"filteredAuxiliaryAssets":2,"auxiliaryAssetsSize":221520},"app":{"name":"app","assets":[{"name":"webpack-runtime-37ea483c46c3e5d7bb05.js","size":5204},{"name":"framework-922e6c69dba211002120.js","size":128957},{"name":"app-d568e612a6f114b73774.js","size":68594}],"filteredAssets":0,"assetsSize":202755,"filteredAuxiliaryAssets":3,"auxiliaryAssetsSize":651744},"component---src-pages-404-js":{"name":"component---src-pages-404-js","assets":[{"name":"styles.457773932d52d28da380.css","size":5414},{"name":"commons-5ebb68e3b5573358db8c.js","size":16892},{"name":"component---src-pages-404-js-f81c3d3d030fd79460df.js","size":491}],"filteredAssets":0,"assetsSize":22797,"filteredAuxiliaryAssets":2,"auxiliaryAssetsSize":70657},"component---src-pages-index-js":{"name":"component---src-pages-index-js","assets":[{"name":"styles.457773932d52d28da380.css","size":5414},{"name":"a9a7754c-eea5fd8e463560bdf3ac.js","size":1667},{"name":"commons-5ebb68e3b5573358db8c.js","size":16892},{"name":"component---src-pages-index-js-3264d447baa68cc3f806.js","size":82489}],"filteredAssets":0,"assetsSize":106462,"filteredAuxiliaryAssets":3,"auxiliaryAssetsSize":916163},"component---src-pages-profile-js":{"name":"component---src-pages-profile-js","assets":[{"name":"styles.457773932d52d28da380.css","size":5414},{"name":"commons-5ebb68e3b5573358db8c.js","size":16892},{"name":"component---src-pages-profile-js-a59fb6017f8d5df34c31.js","size":1098}],"filteredAssets":0,"assetsSize":23404,"filteredAuxiliaryAssets":2,"auxiliaryAssetsSize":71283},"component---src-pages-site-tsx":{"name":"component---src-pages-site-tsx","assets":[{"name":"styles.457773932d52d28da380.css","size":5414},{"name":"commons-5ebb68e3b5573358db8c.js","size":16892},{"name":"component---src-pages-site-tsx-9591cdbd1435207998d2.js","size":2907}],"filteredAssets":0,"assetsSize":25213,"filteredAuxiliaryAssets":2,"auxiliaryAssetsSize":76847},"component---src-pages-skill-js":{"name":"component---src-pages-skill-js","assets":[{"name":"styles.457773932d52d28da380.css","size":5414},{"name":"0f1ac474-325beefd3bdd5e6f9dac.js","size":70861},{"name":"commons-5ebb68e3b5573358db8c.js","size":16892},{"name":"component---src-pages-skill-js-77612b4062e9ee709d81.js","size":66632}],"filteredAssets":0,"assetsSize":159799,"filteredAuxiliaryAssets":3,"auxiliaryAssetsSize":649971}},"assetsByChunkName":{"polyfill":["webpack-runtime-37ea483c46c3e5d7bb05.js","polyfill-2a1c0a52cb0b7a0205e1.js"],"app":["webpack-runtime-37ea483c46c3e5d7bb05.js","framework-922e6c69dba211002120.js","app-d568e612a6f114b73774.js"],"component---src-pages-404-js":["styles.457773932d52d28da380.css","commons-5ebb68e3b5573358db8c.js","component---src-pages-404-js-f81c3d3d030fd79460df.js"],"component---src-pages-index-js":["styles.457773932d52d28da380.css","a9a7754c-eea5fd8e463560bdf3ac.js","commons-5ebb68e3b5573358db8c.js","component---src-pages-index-js-3264d447baa68cc3f806.js"],"component---src-pages-profile-js":["styles.457773932d52d28da380.css","commons-5ebb68e3b5573358db8c.js","component---src-pages-profile-js-a59fb6017f8d5df34c31.js"],"component---src-pages-site-tsx":["styles.457773932d52d28da380.css","commons-5ebb68e3b5573358db8c.js","component---src-pages-site-tsx-9591cdbd1435207998d2.js"],"component---src-pages-skill-js":["styles.457773932d52d28da380.css","0f1ac474-325beefd3bdd5e6f9dac.js","commons-5ebb68e3b5573358db8c.js","component---src-pages-skill-js-77612b4062e9ee709d81.js"]},"childAssetsByChunkName":{}}